SnakeCore/__init__.py
SnakeCore/graphics_and_images.py
SnakeCore/main.py
snakecore-0.0.4.dist-info/METADATA
snakecore-0.0.4.dist-info/WHEEL
snakecore-0.0.4.dist-info/licenses/LICENSE
snakecore-0.0.4.dist-info/RECORD
