Metadata-Version: 2.4
Name: SnakeCore
Version: 0.0.4
Summary: Python library for education and experience
Project-URL: Homepage, https://gitlab.mai.ru/PrivalovAA/snakecore
Project-URL: Issues, https://gitlab.mai.ru/PrivalovAA/snakecore
Author-email: "aa.privalov" <aa.priwalow@yandex.ru>
License-File: LICENSE
Classifier: License :: OSI Approved :: MIT License
Classifier: Operating System :: OS Independent
Classifier: Programming Language :: Python :: 3
Requires-Python: >=3.10.0
